[
  {
    "rows": [
      [
        {
          "name": "attribute"
        },
        false
      ],
      [
        {
          "name": "scope"
        },
        false
      ],
      [
        {
          "name": "channel"
        },
        false
      ],
      [
        {
          "name": "isRequired"
        },
        false
      ],
      [
        {
          "name": "language"
        },
        false
      ],
      [
        {
          "name": "languages"
        },
        false
      ]
    ],
    "style": "default",
    "label": ""
  }
]